sideload_nu_0_bin_6633e578acd3cb34a842086a/__init__.py
sideload_nu_0_bin_6633e578acd3cb34a842086a/nu-0.93.0-x86_64-pc-windows-msvc.zip
sideload_nu_0_bin_6633e578acd3cb34a842086a-1.0.0.dist-info/METADATA
sideload_nu_0_bin_6633e578acd3cb34a842086a-1.0.0.dist-info/WHEEL
sideload_nu_0_bin_6633e578acd3cb34a842086a-1.0.0.dist-info/top_level.txt
sideload_nu_0_bin_6633e578acd3cb34a842086a-1.0.0.dist-info/RECORD
